psychopy_theme/__init__.py
psychopy_theme/globaltoc.html
psychopy_theme/header.html
psychopy_theme/homepage_header.html
psychopy_theme/layout.html
psychopy_theme/localtoc.html
psychopy_theme/navbar.html
psychopy_theme/navbar_item.html
psychopy_theme/navbarsearchbox.html
psychopy_theme/navbartoc.html
psychopy_theme/relations.html
psychopy_theme/search.html
psychopy_theme/searchbox.html
psychopy_theme/searchresults.html
psychopy_theme/sourcelink.html
psychopy_theme/theme.toml
psychopy_theme/static/UoN_Supported_RGB.png
psychopy_theme/static/basic.css
psychopy_theme/static/bootstrap-sphinx.css_t
psychopy_theme/static/bootstrap-sphinx.js
psychopy_theme/static/bootstrap-sphinx.js_t
psychopy_theme/static/component_wave.svg
psychopy_theme/static/component_wave_double.svg
psychopy_theme/static/doctools.js
psychopy_theme/static/documentation_options.js
psychopy_theme/static/jquery-3.4.1.js
psychopy_theme/static/jquery.js
psychopy_theme/static/language_data.js
psychopy_theme/static/navbar_logo_large.png
psychopy_theme/static/navbar_logo_plugin_dir_large.png
psychopy_theme/static/navbar_logo_plugin_dir_small.png
psychopy_theme/static/navbar_logo_plugin_large.png
psychopy_theme/static/navbar_logo_plugin_small.png
psychopy_theme/static/navbar_logo_small.png
psychopy_theme/static/psychopy.css
psychopy_theme/static/psychopyLogoType3_h240.png
psychopy_theme/static/psychopyLogoType3_h480.png
psychopy_theme/static/psychopyLogoTypeAndStraps_h480.png
psychopy_theme/static/psychopyLogoType_h480.png
psychopy_theme/static/psychopyOnly3_h480.png
psychopy_theme/static/psychopyStrapEasy.png
psychopy_theme/static/psychopyStrapFlexible.png
psychopy_theme/static/psychopyStrapOnline3.png
psychopy_theme/static/psychopyStrapPrecise.png
psychopy_theme/static/pygments.css
psychopy_theme/static/searchtools.js
psychopy_theme/static/swiper-bundle.css
psychopy_theme/static/swiper-bundle.js
psychopy_theme/static/testimonial.css
psychopy_theme/static/testimonial.js
psychopy_sphinx_theme-0.0.9.dist-info/METADATA
psychopy_sphinx_theme-0.0.9.dist-info/WHEEL
psychopy_sphinx_theme-0.0.9.dist-info/entry_points.txt
psychopy_sphinx_theme-0.0.9.dist-info/top_level.txt
psychopy_sphinx_theme-0.0.9.dist-info/RECORD
