Metadata-Version: 2.4
Name: psychopy-sphinx-theme
Version: 0.0.9
Summary: Sphinx theme to make docs look like PsychoPy docs
Author-email: Open Science Tools <science@opensceincetools.org>
License: MIT
Project-URL: homepage, https://github.com/psychopy/psychopy-sphinx-theme
Project-URL: changelog, https://github.com/psychopy/psychopy-sphinx-theme/blob/main/CHANGELOG.md
